simpledataengineeringtoolkit/checker.py
simpledataengineeringtoolkit/cleaner.py
simpledataengineeringtoolkit/staticvalues.py
simpledataengineeringtoolkit-0.1.3.dist-info/METADATA
simpledataengineeringtoolkit-0.1.3.dist-info/WHEEL
simpledataengineeringtoolkit-0.1.3.dist-info/top_level.txt
simpledataengineeringtoolkit-0.1.3.dist-info/RECORD
